fpga_project/src/pwm_gen.v
`timescale 1ns/1ps
// ============================================================================
// pwm_gen.v -- fixed-frequency PWM generator
//
//   clk     : system clock (50 MHz on LCKFB LogicPi FPGA-G1)
//   rst_n   : asynchronous reset, active low
//   pwm_out : PWM output, high for DUTY_PCT percent of every period
//
//   PERIOD   = CLK_FREQ / PWM_FREQ      (clocks per PWM period)
//   DUTY_CNT = PERIOD * DUTY_PCT / 100  (clocks high per period)
//
//   All counters are synchronous to clk; reset is asynchronous.
//   Counter width 32 bits is oversized but synthesis trims unused bits.
// ============================================================================
module pwm_gen #(
    parameter integer CLK_FREQ = 50_000_000,   // Hz
    parameter integer PWM_FREQ = 20_000,       // Hz
    parameter integer DUTY_PCT = 30            // 0 .. 100
) (
    input  wire clk,
    input  wire rst_n,
    output reg  pwm_out
);

    localparam [31:0] PERIOD   = CLK_FREQ / PWM_FREQ;             // 2500 @ 50MHz / 20kHz
    localparam [31:0] DUTY_CNT = (CLK_FREQ / PWM_FREQ) * DUTY_PCT / 100;  // 750 @ 30%

    reg [31:0] cnt;

    // ---- period counter: 0 .. PERIOD-1 ----
    always @(posedge clk or negedge rst_n) begin
        if (!rst_n)
            cnt <= 32'd0;
        else if (cnt >= PERIOD - 32'd1)
            cnt <= 32'd0;
        else
            cnt <= cnt + 32'd1;
    end

    // ---- compare: high while cnt < DUTY_CNT ----
    always @(posedge clk or negedge rst_n) begin
        if (!rst_n)
            pwm_out <= 1'b0;
        else
            pwm_out <= (cnt < DUTY_CNT) ? 1'b1 : 1'b0;
    end

endmodule

fpga_project/sim/pwm_gen_tb.v
// ============================================================================
// pwm_gen_tb.v -- self-checking testbench for pwm_gen
//
//   Kept OUT of the Gowin project (lives in sim/, never added to the .gprj).
//   Parameters are scaled down 50000x so the whole check runs in a few us:
//       CLK_FREQ = 1000, PWM_FREQ = 10, DUTY_PCT = 30
//       -> PERIOD = 100 clocks, DUTY = 30 clocks
//
//   Run:
//       iverilog -o pwm_gen_tb.vvp pwm_gen_tb.v ../src/pwm_gen.v
//       vvp pwm_gen_tb.vvp
//
//   Prints PASS / FAIL. pwm_out is sampled on negedges, i.e. half a clock
//   after each posedge, so there is no race with the DUT's nonblocking
//   assignment.
// ============================================================================
`timescale 1ns/1ps

module pwm_gen_tb;

    localparam integer TB_CLK_FREQ = 1000;
    localparam integer TB_PWM_FREQ = 10;
    localparam integer TB_DUTY_PCT = 30;

    localparam integer EXP_PERIOD = TB_CLK_FREQ / TB_PWM_FREQ;              // 100
    localparam integer EXP_HIGH   = EXP_PERIOD * TB_DUTY_PCT / 100;         // 30
    localparam integer EXP_LOW    = EXP_PERIOD - EXP_HIGH;                  // 70

    reg  clk   = 1'b0;
    reg  rst_n = 1'b0;
    wire pwm_out;

    integer errors = 0;
    integer high_cnt;
    integer low_cnt;
    integer p;

    pwm_gen #(
        .CLK_FREQ (TB_CLK_FREQ),
        .PWM_FREQ (TB_PWM_FREQ),
        .DUTY_PCT (TB_DUTY_PCT)
    ) dut (
        .clk     (clk),
        .rst_n   (rst_n),
        .pwm_out (pwm_out)
    );

    always #5 clk = ~clk;      // 10 ns period -> 100 MHz "clock", 10 clocks per PWM period

    initial begin
        $dumpfile("pwm_gen_tb.vcd");
        $dumpvars(0, pwm_gen_tb);

        // ---- 1. output must stay low while reset is asserted ----
        repeat (5) @(negedge clk);
        if (pwm_out !== 1'b0) begin
            $display("FAIL: pwm_out = %b during reset, expected 0", pwm_out);
            errors = errors + 1;
        end

        rst_n = 1'b1;

        // ---- 2. align to the first high phase ----
        @(negedge clk);
        while (pwm_out !== 1'b1) @(negedge clk);

        // ---- 3. measure 3 consecutive periods ----
        for (p = 0; p < 3; p = p + 1) begin
            high_cnt = 0;
            low_cnt  = 0;

            while (pwm_out === 1'b1) begin
                high_cnt = high_cnt + 1;
                @(negedge clk);
            end
            while (pwm_out === 1'b0) begin
                low_cnt = low_cnt + 1;
                @(negedge clk);
            end

            $display("period %0d : high = %0d, low = %0d  (expect %0d / %0d)",
                     p, high_cnt, low_cnt, EXP_HIGH, EXP_LOW);

            if (high_cnt !== EXP_HIGH) begin
                $display("FAIL: high phase is %0d clocks, expected %0d", high_cnt, EXP_HIGH);
                errors = errors + 1;
            end
            if (low_cnt !== EXP_LOW) begin
                $display("FAIL: low phase is %0d clocks, expected %0d", low_cnt, EXP_LOW);
                errors = errors + 1;
            end
        end

        if (errors == 0)
            $display("PASS: pwm_gen verified - %0d clocks high / %0d clocks low per period",
                     EXP_HIGH, EXP_LOW);
        else
            $display("FAIL: %0d check(s) failed", errors);

        $finish;
    end

endmodule

fpga_project/sim/pwm_gen_tb.vcd
$date
	Sat Sep 26 13:39:43 2026
$end
$version
	Icarus Verilog
$end
$timescale
	1ps
$end
$scope module pwm_gen_tb $end
$var wire 1 ! pwm_out $end
$var parameter 32 " EXP_HIGH $end
$var parameter 32 # EXP_LOW $end
$var parameter 32 $ EXP_PERIOD $end
$var parameter 32 % TB_CLK_FREQ $end
$var parameter 32 & TB_DUTY_PCT $end
$var parameter 32 ' TB_PWM_FREQ $end
$var reg 1 ( clk $end
$var reg 1 ) rst_n $end
$var integer 32 * errors [31:0] $end
$var integer 32 + high_cnt [31:0] $end
$var integer 32 , low_cnt [31:0] $end
$var integer 32 - p [31:0] $end
$scope module dut $end
$var wire 1 ( clk $end
$var wire 1 ) rst_n $end
$var parameter 32 . CLK_FREQ $end
$var parameter 32 / DUTY_CNT $end
$var parameter 32 0 DUTY_PCT $end
$var parameter 32 1 PERIOD $end
$var parameter 32 2 PWM_FREQ $end
$var reg 32 3 cnt [31:0] $end
$var reg 1 ! pwm_out $end
$upscope $end
$upscope $end
$enddefinitions $end
$comment Show the parameter values. $end
$dumpall
b1010 2
b1100100 1
b11110 0
b11110 /
b1111101000 .
b1010 '
b11110 &
b1111101000 %
b1100100 $
b1000110 #
b11110 "
$end
#0
$dumpvars
b0 3
bx -
bx ,
bx +
b0 *
0)
0(
0!
$end
#5000
1(
#10000
0(
#15000
1(
#20000
0(
#25000
1(
#30000
0(
#35000
1(
#40000
0(
#45000
1(
#50000
1)
0(
#55000
b1 3
1!
1(
#60000
b0 ,
b1 +
b0 -
0(
#65000
b10 3
1(
#70000
b10 +
0(
#75000
b11 3
1(
#80000
b11 +
0(
#85000
b100 3
1(
#90000
b100 +
0(
#95000
b101 3
1(
#100000
b101 +
0(
#105000
b110 3
1(
#110000
b110 +
0(
#115000
b111 3
1(
#120000
b111 +
0(
#125000
b1000 3
1(
#130000
b1000 +
0(
#135000
b1001 3
1(
#140000
b1001 +
0(
#145000
b1010 3
1(
#150000
b1010 +
0(
#155000
b1011 3
1(
#160000
b1011 +
0(
#165000
b1100 3
1(
#170000
b1100 +
0(
#175000
b1101 3
1(
#180000
b1101 +
0(
#185000
b1110 3
1(
#190000
b1110 +
0(
#195000
b1111 3
1(
#200000
b1111 +
0(
#205000
b10000 3
1(
#210000
b10000 +
0(
#215000
b10001 3
1(
#220000
b10001 +
0(
#225000
b10010 3
1(
#230000
b10010 +
0(
#235000
b10011 3
1(
#240000
b10011 +
0(
#245000
b10100 3
1(
#250000
b10100 +
0(
#255000
b10101 3
1(
#260000
b10101 +
0(
#265000
b10110 3
1(
#270000
b10110 +
0(
#275000
b10111 3
1(
#280000
b10111 +
0(
#285000
b11000 3
1(
#290000
b11000 +
0(
#295000
b11001 3
1(
#300000
b11001 +
0(
#305000
b11010 3
1(
#310000
b11010 +
0(
#315000
b11011 3
1(
#320000
b11011 +
0(
#325000
b11100 3
1(
#330000
b11100 +
0(
#335000
b11101 3
1(
#340000
b11101 +
0(
#345000
b11110 3
1(
#350000
b11110 +
0(
#355000
b11111 3
0!
1(
#360000
b1 ,
0(
#365000
b100000 3
1(
#370000
b10 ,
0(
#375000
b100001 3
1(
#380000
b11 ,
0(
#385000
b100010 3
1(
#390000
b100 ,
0(
#395000
b100011 3
1(
#400000
b101 ,
0(
#405000
b100100 3
1(
#410000
b110 ,
0(
#415000
b100101 3
1(
#420000
b111 ,
0(
#425000
b100110 3
1(
#430000
b1000 ,
0(
#435000
b100111 3
1(
#440000
b1001 ,
0(
#445000
b101000 3
1(
#450000
b1010 ,
0(
#455000
b101001 3
1(
#460000
b1011 ,
0(
#465000
b101010 3
1(
#470000
b1100 ,
0(
#475000
b101011 3
1(
#480000
b1101 ,
0(
#485000
b101100 3
1(
#490000
b1110 ,
0(
#495000
b101101 3
1(
#500000
b1111 ,
0(
#505000
b101110 3
1(
#510000
b10000 ,
0(
#515000
b101111 3
1(
#520000
b10001 ,
0(
#525000
b110000 3
1(
#530000
b10010 ,
0(
#535000
b110001 3
1(
#540000
b10011 ,
0(
#545000
b110010 3
1(
#550000
b10100 ,
0(
#555000
b110011 3
1(
#560000
b10101 ,
0(
#565000
b110100 3
1(
#570000
b10110 ,
0(
#575000
b110101 3
1(
#580000
b10111 ,
0(
#585000
b110110 3
1(
#590000
b11000 ,
0(
#595000
b110111 3
1(
#600000
b11001 ,
0(
#605000
b111000 3
1(
#610000
b11010 ,
0(
#615000
b111001 3
1(
#620000
b11011 ,
0(
#625000
b111010 3
1(
#630000
b11100 ,
0(
#635000
b111011 3
1(
#640000
b11101 ,
0(
#645000
b111100 3
1(
#650000
b11110 ,
0(
#655000
b111101 3
1(
#660000
b11111 ,
0(
#665000
b111110 3
1(
#670000
b100000 ,
0(
#675000
b111111 3
1(
#680000
b100001 ,
0(
#685000
b1000000 3
1(
#690000
b100010 ,
0(
#695000
b1000001 3
1(
#700000
b100011 ,
0(
#705000
b1000010 3
1(
#710000
b100100 ,
0(
#715000
b1000011 3
1(
#720000
b100101 ,
0(
#725000
b1000100 3
1(
#730000
b100110 ,
0(
#735000
b1000101 3
1(
#740000
b100111 ,
0(
#745000
b1000110 3
1(
#750000
b101000 ,
0(
#755000
b1000111 3
1(
#760000
b101001 ,
0(
#765000
b1001000 3
1(
#770000
b101010 ,
0(
#775000
b1001001 3
1(
#780000
b101011 ,
0(
#785000
b1001010 3
1(
#790000
b101100 ,
0(
#795000
b1001011 3
1(
#800000
b101101 ,
0(
#805000
b1001100 3
1(
#810000
b101110 ,
0(
#815000
b1001101 3
1(
#820000
b101111 ,
0(
#825000
b1001110 3
1(
#830000
b110000 ,
0(
#835000
b1001111 3
1(
#840000
b110001 ,
0(
#845000
b1010000 3
1(
#850000
b110010 ,
0(
#855000
b1010001 3
1(
#860000
b110011 ,
0(
#865000
b1010010 3
1(
#870000
b110100 ,
0(
#875000
b1010011 3
1(
#880000
b110101 ,
0(
#885000
b1010100 3
1(
#890000
b110110 ,
0(
#895000
b1010101 3
1(
#900000
b110111 ,
0(
#905000
b1010110 3
1(
#910000
b111000 ,
0(
#915000
b1010111 3
1(
#920000
b111001 ,
0(
#925000
b1011000 3
1(
#930000
b111010 ,
0(
#935000
b1011001 3
1(
#940000
b111011 ,
0(
#945000
b1011010 3
1(
#950000
b111100 ,
0(
#955000
b1011011 3
1(
#960000
b111101 ,
0(
#965000
b1011100 3
1(
#970000
b111110 ,
0(
#975000
b1011101 3
1(
#980000
b111111 ,
0(
#985000
b1011110 3
1(
#990000
b1000000 ,
0(
#995000
b1011111 3
1(
#1000000
b1000001 ,
0(
#1005000
b1100000 3
1(
#1010000
b1000010 ,
0(
#1015000
b1100001 3
1(
#1020000
b1000011 ,
0(
#1025000
b1100010 3
1(
#1030000
b1000100 ,
0(
#1035000
b1100011 3
1(
#1040000
b1000101 ,
0(
#1045000
b0 3
1(
#1050000
b1000110 ,
0(
#1055000
b1 3
1!
1(
#1060000
b0 ,
b1 +
b1 -
0(
#1065000
b10 3
1(
#1070000
b10 +
0(
#1075000
b11 3
1(
#1080000
b11 +
0(
#1085000
b100 3
1(
#1090000
b100 +
0(
#1095000
b101 3
1(
#1100000
b101 +
0(
#1105000
b110 3
1(
#1110000
b110 +
0(
#1115000
b111 3
1(
#1120000
b111 +
0(
#1125000
b1000 3
1(
#1130000
b1000 +
0(
#1135000
b1001 3
1(
#1140000
b1001 +
0(
#1145000
b1010 3
1(
#1150000
b1010 +
0(
#1155000
b1011 3
1(
#1160000
b1011 +
0(
#1165000
b1100 3
1(
#1170000
b1100 +
0(
#1175000
b1101 3
1(
#1180000
b1101 +
0(
#1185000
b1110 3
1(
#1190000
b1110 +
0(
#1195000
b1111 3
1(
#1200000
b1111 +
0(
#1205000
b10000 3
1(
#1210000
b10000 +
0(
#1215000
b10001 3
1(
#1220000
b10001 +
0(
#1225000
b10010 3
1(
#1230000
b10010 +
0(
#1235000
b10011 3
1(
#1240000
b10011 +
0(
#1245000
b10100 3
1(
#1250000
b10100 +
0(
#1255000
b10101 3
1(
#1260000
b10101 +
0(
#1265000
b10110 3
1(
#1270000
b10110 +
0(
#1275000
b10111 3
1(
#1280000
b10111 +
0(
#1285000
b11000 3
1(
#1290000
b11000 +
0(
#1295000
b11001 3
1(
#1300000
b11001 +
0(
#1305000
b11010 3
1(
#1310000
b11010 +
0(
#1315000
b11011 3
1(
#1320000
b11011 +
0(
#1325000
b11100 3
1(
#1330000
b11100 +
0(
#1335000
b11101 3
1(
#1340000
b11101 +
0(
#1345000
b11110 3
1(
#1350000
b11110 +
0(
#1355000
b11111 3
0!
1(
#1360000
b1 ,
0(
#1365000
b100000 3
1(
#1370000
b10 ,
0(
#1375000
b100001 3
1(
#1380000
b11 ,
0(
#1385000
b100010 3
1(
#1390000
b100 ,
0(
#1395000
b100011 3
1(
#1400000
b101 ,
0(
#1405000
b100100 3
1(
#1410000
b110 ,
0(
#1415000
b100101 3
1(
#1420000
b111 ,
0(
#1425000
b100110 3
1(
#1430000
b1000 ,
0(
#1435000
b100111 3
1(
#1440000
b1001 ,
0(
#1445000
b101000 3
1(
#1450000
b1010 ,
0(
#1455000
b101001 3
1(
#1460000
b1011 ,
0(
#1465000
b101010 3
1(
#1470000
b1100 ,
0(
#1475000
b101011 3
1(
#1480000
b1101 ,
0(
#1485000
b101100 3
1(
#1490000
b1110 ,
0(
#1495000
b101101 3
1(
#1500000
b1111 ,
0(
#1505000
b101110 3
1(
#1510000
b10000 ,
0(
#1515000
b101111 3
1(
#1520000
b10001 ,
0(
#1525000
b110000 3
1(
#1530000
b10010 ,
0(
#1535000
b110001 3
1(
#1540000
b10011 ,
0(
#1545000
b110010 3
1(
#1550000
b10100 ,
0(
#1555000
b110011 3
1(
#1560000
b10101 ,
0(
#1565000
b110100 3
1(
#1570000
b10110 ,
0(
#1575000
b110101 3
1(
#1580000
b10111 ,
0(
#1585000
b110110 3
1(
#1590000
b11000 ,
0(
#1595000
b110111 3
1(
#1600000
b11001 ,
0(
#1605000
b111000 3
1(
#1610000
b11010 ,
0(
#1615000
b111001 3
1(
#1620000
b11011 ,
0(
#1625000
b111010 3
1(
#1630000
b11100 ,
0(
#1635000
b111011 3
1(
#1640000
b11101 ,
0(
#1645000
b111100 3
1(
#1650000
b11110 ,
0(
#1655000
b111101 3
1(
#1660000
b11111 ,
0(
#1665000
b111110 3
1(
#1670000
b100000 ,
0(
#1675000
b111111 3
1(
#1680000
b100001 ,
0(
#1685000
b1000000 3
1(
#1690000
b100010 ,
0(
#1695000
b1000001 3
1(
#1700000
b100011 ,
0(
#1705000
b1000010 3
1(
#1710000
b100100 ,
0(
#1715000
b1000011 3
1(
#1720000
b100101 ,
0(
#1725000
b1000100 3
1(
#1730000
b100110 ,
0(
#1735000
b1000101 3
1(
#1740000
b100111 ,
0(
#1745000
b1000110 3
1(
#1750000
b101000 ,
0(
#1755000
b1000111 3
1(
#1760000
b101001 ,
0(
#1765000
b1001000 3
1(
#1770000
b101010 ,
0(
#1775000
b1001001 3
1(
#1780000
b101011 ,
0(
#1785000
b1001010 3
1(
#1790000
b101100 ,
0(
#1795000
b1001011 3
1(
#1800000
b101101 ,
0(
#1805000
b1001100 3
1(
#1810000
b101110 ,
0(
#1815000
b1001101 3
1(
#1820000
b101111 ,
0(
#1825000
b1001110 3
1(
#1830000
b110000 ,
0(
#1835000
b1001111 3
1(
#1840000
b110001 ,
0(
#1845000
b1010000 3
1(
#1850000
b110010 ,
0(
#1855000
b1010001 3
1(
#1860000
b110011 ,
0(
#1865000
b1010010 3
1(
#1870000
b110100 ,
0(
#1875000
b1010011 3
1(
#1880000
b110101 ,
0(
#1885000
b1010100 3
1(
#1890000
b110110 ,
0(
#1895000
b1010101 3
1(
#1900000
b110111 ,
0(
#1905000
b1010110 3
1(
#1910000
b111000 ,
0(
#1915000
b1010111 3
1(
#1920000
b111001 ,
0(
#1925000
b1011000 3
1(
#1930000
b111010 ,
0(
#1935000
b1011001 3
1(
#1940000
b111011 ,
0(
#1945000
b1011010 3
1(
#1950000
b111100 ,
0(
#1955000
b1011011 3
1(
#1960000
b111101 ,
0(
#1965000
b1011100 3
1(
#1970000
b111110 ,
0(
#1975000
b1011101 3
1(
#1980000
b111111 ,
0(
#1985000
b1011110 3
1(
#1990000
b1000000 ,
0(
#1995000
b1011111 3
1(
#2000000
b1000001 ,
0(
#2005000
b1100000 3
1(
#2010000
b1000010 ,
0(
#2015000
b1100001 3
1(
#2020000
b1000011 ,
0(
#2025000
b1100010 3
1(
#2030000
b1000100 ,
0(
#2035000
b1100011 3
1(
#2040000
b1000101 ,
0(
#2045000
b0 3
1(
#2050000
b1000110 ,
0(
#2055000
b1 3
1!
1(
#2060000
b0 ,
b1 +
b10 -
0(
#2065000
b10 3
1(
#2070000
b10 +
0(
#2075000
b11 3
1(
#2080000
b11 +
0(
#2085000
b100 3
1(
#2090000
b100 +
0(
#2095000
b101 3
1(
#2100000
b101 +
0(
#2105000
b110 3
1(
#2110000
b110 +
0(
#2115000
b111 3
1(
#2120000
b111 +
0(
#2125000
b1000 3
1(
#2130000
b1000 +
0(
#2135000
b1001 3
1(
#2140000
b1001 +
0(
#2145000
b1010 3
1(
#2150000
b1010 +
0(
#2155000
b1011 3
1(
#2160000
b1011 +
0(
#2165000
b1100 3
1(
#2170000
b1100 +
0(
#2175000
b1101 3
1(
#2180000
b1101 +
0(
#2185000
b1110 3
1(
#2190000
b1110 +
0(
#2195000
b1111 3
1(
#2200000
b1111 +
0(
#2205000
b10000 3
1(
#2210000
b10000 +
0(
#2215000
b10001 3
1(
#2220000
b10001 +
0(
#2225000
b10010 3
1(
#2230000
b10010 +
0(
#2235000
b10011 3
1(
#2240000
b10011 +
0(
#2245000
b10100 3
1(
#2250000
b10100 +
0(
#2255000
b10101 3
1(
#2260000
b10101 +
0(
#2265000
b10110 3
1(
#2270000
b10110 +
0(
#2275000
b10111 3
1(
#2280000
b10111 +
0(
#2285000
b11000 3
1(
#2290000
b11000 +
0(
#2295000
b11001 3
1(
#2300000
b11001 +
0(
#2305000
b11010 3
1(
#2310000
b11010 +
0(
#2315000
b11011 3
1(
#2320000
b11011 +
0(
#2325000
b11100 3
1(
#2330000
b11100 +
0(
#2335000
b11101 3
1(
#2340000
b11101 +
0(
#2345000
b11110 3
1(
#2350000
b11110 +
0(
#2355000
b11111 3
0!
1(
#2360000
b1 ,
0(
#2365000
b100000 3
1(
#2370000
b10 ,
0(
#2375000
b100001 3
1(
#2380000
b11 ,
0(
#2385000
b100010 3
1(
#2390000
b100 ,
0(
#2395000
b100011 3
1(
#2400000
b101 ,
0(
#2405000
b100100 3
1(
#2410000
b110 ,
0(
#2415000
b100101 3
1(
#2420000
b111 ,
0(
#2425000
b100110 3
1(
#2430000
b1000 ,
0(
#2435000
b100111 3
1(
#2440000
b1001 ,
0(
#2445000
b101000 3
1(
#2450000
b1010 ,
0(
#2455000
b101001 3
1(
#2460000
b1011 ,
0(
#2465000
b101010 3
1(
#2470000
b1100 ,
0(
#2475000
b101011 3
1(
#2480000
b1101 ,
0(
#2485000
b101100 3
1(
#2490000
b1110 ,
0(
#2495000
b101101 3
1(
#2500000
b1111 ,
0(
#2505000
b101110 3
1(
#2510000
b10000 ,
0(
#2515000
b101111 3
1(
#2520000
b10001 ,
0(
#2525000
b110000 3
1(
#2530000
b10010 ,
0(
#2535000
b110001 3
1(
#2540000
b10011 ,
0(
#2545000
b110010 3
1(
#2550000
b10100 ,
0(
#2555000
b110011 3
1(
#2560000
b10101 ,
0(
#2565000
b110100 3
1(
#2570000
b10110 ,
0(
#2575000
b110101 3
1(
#2580000
b10111 ,
0(
#2585000
b110110 3
1(
#2590000
b11000 ,
0(
#2595000
b110111 3
1(
#2600000
b11001 ,
0(
#2605000
b111000 3
1(
#2610000
b11010 ,
0(
#2615000
b111001 3
1(
#2620000
b11011 ,
0(
#2625000
b111010 3
1(
#2630000
b11100 ,
0(
#2635000
b111011 3
1(
#2640000
b11101 ,
0(
#2645000
b111100 3
1(
#2650000
b11110 ,
0(
#2655000
b111101 3
1(
#2660000
b11111 ,
0(
#2665000
b111110 3
1(
#2670000
b100000 ,
0(
#2675000
b111111 3
1(
#2680000
b100001 ,
0(
#2685000
b1000000 3
1(
#2690000
b100010 ,
0(
#2695000
b1000001 3
1(
#2700000
b100011 ,
0(
#2705000
b1000010 3
1(
#2710000
b100100 ,
0(
#2715000
b1000011 3
1(
#2720000
b100101 ,
0(
#2725000
b1000100 3
1(
#2730000
b100110 ,
0(
#2735000
b1000101 3
1(
#2740000
b100111 ,
0(
#2745000
b1000110 3
1(
#2750000
b101000 ,
0(
#2755000
b1000111 3
1(
#2760000
b101001 ,
0(
#2765000
b1001000 3
1(
#2770000
b101010 ,
0(
#2775000
b1001001 3
1(
#2780000
b101011 ,
0(
#2785000
b1001010 3
1(
#2790000
b101100 ,
0(
#2795000
b1001011 3
1(
#2800000
b101101 ,
0(
#2805000
b1001100 3
1(
#2810000
b101110 ,
0(
#2815000
b1001101 3
1(
#2820000
b101111 ,
0(
#2825000
b1001110 3
1(
#2830000
b110000 ,
0(
#2835000
b1001111 3
1(
#2840000
b110001 ,
0(
#2845000
b1010000 3
1(
#2850000
b110010 ,
0(
#2855000
b1010001 3
1(
#2860000
b110011 ,
0(
#2865000
b1010010 3
1(
#2870000
b110100 ,
0(
#2875000
b1010011 3
1(
#2880000
b110101 ,
0(
#2885000
b1010100 3
1(
#2890000
b110110 ,
0(
#2895000
b1010101 3
1(
#2900000
b110111 ,
0(
#2905000
b1010110 3
1(
#2910000
b111000 ,
0(
#2915000
b1010111 3
1(
#2920000
b111001 ,
0(
#2925000
b1011000 3
1(
#2930000
b111010 ,
0(
#2935000
b1011001 3
1(
#2940000
b111011 ,
0(
#2945000
b1011010 3
1(
#2950000
b111100 ,
0(
#2955000
b1011011 3
1(
#2960000
b111101 ,
0(
#2965000
b1011100 3
1(
#2970000
b111110 ,
0(
#2975000
b1011101 3
1(
#2980000
b111111 ,
0(
#2985000
b1011110 3
1(
#2990000
b1000000 ,
0(
#2995000
b1011111 3
1(
#3000000
b1000001 ,
0(
#3005000
b1100000 3
1(
#3010000
b1000010 ,
0(
#3015000
b1100001 3
1(
#3020000
b1000011 ,
0(
#3025000
b1100010 3
1(
#3030000
b1000100 ,
0(
#3035000
b1100011 3
1(
#3040000
b1000101 ,
0(
#3045000
b0 3
1(
#3050000
b1000110 ,
0(
#3055000
b1 3
1!
1(
#3060000
b11 -
0(
